setup.py
contemplate/__init__.py
contemplate/__main__.py
contemplate.egg-info/PKG-INFO
contemplate.egg-info/SOURCES.txt
contemplate.egg-info/dependency_links.txt
contemplate.egg-info/entry_points.txt
contemplate.egg-info/top_level.txt
contemplate/engine/__init__.py
contemplate/engine/format.py
contemplate/parser/__init__.py
contemplate/parser/env.py
contemplate/parser/json.py
contemplate/source/__init__.py
contemplate/source/file.py