Metadata-Version: 1.1
Name: contemplate
Version: 0.1
Summary: multi templating engines command-line interface
Home-page: https://github.com/nlm/contemplate
Author: Nicolas Limage
Author-email: github@xephon.org
License: MIT
Keywords: content template command-line
Platform: UNKNOWN
Classifier: Development Status :: 4 - Beta
Classifier: Environment :: Console
Classifier: License :: OSI Approved :: MIT License
Classifier: Operating System :: OS Independent
Classifier: Programming Language :: Python
